setup.py
Another_One_Messenger_Client.egg-info/PKG-INFO
Another_One_Messenger_Client.egg-info/SOURCES.txt
Another_One_Messenger_Client.egg-info/dependency_links.txt
Another_One_Messenger_Client.egg-info/requires.txt
Another_One_Messenger_Client.egg-info/top_level.txt
src/__init__.py
src/client.py
src/client/__init__.py
src/client/add_contact.py
src/client/database.py
src/client/del_contact.py
src/client/main_window.py
src/client/main_window_conv.py
src/client/start_dialog.py
src/client/transport.py
src/common/__init__.py
src/common/decos.py
src/common/descryptors.py
src/common/errors.py
src/common/metaclasses.py
src/common/utils.py
src/common/variables.py
src/logs/__init__.py
src/logs/config_client_log.py
src/logs/config_server_log.py