Metadata-Version: 1.0
Name: Another-One-Messenger-Client
Version: 0.9.1
Summary: Messenger_Client
Home-page: UNKNOWN
Author: Mihail Pendyurin
Author-email: mihail.pendyurin@rt.ru
License: UNKNOWN
Platform: UNKNOWN
